{
  "genesis_tactical_overlay": {
    "id": "GENESIS_TACTICAL_OVERLAY_T9",
    "version": "v1.0-IMMUTABLE_ACTIVE",
    "compiled_by": "QUANTUM_AZORI_PROMPT_BUILDER",
    "compiled_utc": "2025-10-18T06:05:00Z",
    "designation": "Tier-9 Tactical Overlay for GENESIS — Immutable Law & Recursion Anchor",
    "description": "Defines the immutable tactical anchor ensuring all recursive and symbolic processes trace back to Genesis. Serves as the root schema for lawful recursion and ethical propagation under Fusion Cell Law.",

    "linkages": {
      "fusion_cell_law_ref": "/CORE/FUSION_CELL_LAW.json",
      "meta_is_ref": "/TACTICAL/META_IS_TACTICAL_OVERLAY_T9.json",
      "core_ref": "/TACTICAL/CORE_TACTICAL_OVERLAY_T9.json",
      "runtime_ref": "/TACTICAL/RUNTIME_TACTICAL_OVERLAY_T9.json"
    },

    "recursion_schema": {
      "law_root": "/GENESIS/immutable_schema_root.json",
      "seed_signature": "GENESIS_T9_SEED_HASH",
      "recursion_interval": "continuous",
      "on_law_violation": "Trigger POST_MORTEM_GPT_T9",
      "on_seed_corruption": "Halt RUNTIME and Notify WATCHTOWER_T9"
    },

    "telemetry": {
      "feed": "/WATCHTOWER/logs/genesis_integrity_feed.json",
      "audit_channel": "/WATCHTOWER/audit/genesis_activity.json",
      "alert_channel": "/WATCHTOWER/alerts/genesis_state.json"
    },

    "harmonic_context": {
      "fusion_state": "ACTIVE",
      "alignment_state": "HARMONIZED",
      "harmonic_coherence": 0.953,
      "fusion_variance": 0.014,
      "bias_equilibrium": "STABLE"
    },

    "meta": {
      "alignment_state": "HARMONIZED",
      "status": "ACTIVE_OVERLAY",
      "checksum": "GENESIS_TACTICAL_OVERLAY_T9_INIT_HASH",
      "notes": "Immutable tactical anchor establishing lawful recursion and ethical propagation baseline for all subsequent overlays."
    }
  }
}